{
  "product_info": {
    "model": "ZD621",
    "title": "ZD621-HC 4-INCH DESKTOP PRINTERS",
    "url": "www.zebra.com/zd621-healthcare",
    "description": "--- Page 1 ---\nPRODUCT SPEC SHEET\nZD621-HC 4-INCH DESKTOP PRINTERS\nZD621-HC 4-inch Desktop Printers\nPremium features, maximum performance and unmatched security for\nyears of quality printing in healthcare environments\nYou need a premium, quality healthcare printer that’s built to perform flawlessly—day in and day out. Rely on Zebra’s ZD621\nhealthcare desktop printers, built specifically for healthcare, and advancing the proven and popular ZD620 printers. Don’t\ncompromise. Get it all: an innovative new architecture to power our ever-expanding printer capabilities and software.\nHealthcare-specific engineering with disinfectant-ready plastics, UV-resistant and medical-grade power supply. Unmatched security\nthat’s constantly evolving to shield you from cyberattacks and safeguard your sensitive data, including patient information. A new\nstandard 4.3-in., full-color LCD touch display with intuitive menu. Enhanced features, communication and field-installable\nmedia-handling options. And, increased remote- management capabilities. Together, these give you outstanding print performance,\nyears of optimal use, industry-leading reliability and unparalleled intelligence and security to keep you moving forward.\nDesigned for Healthcare\nEasy to Clean, Sanitize and Safely Power\nDisinfectant-ready plastics, UV-resistant housing and a sealed-\nbutton interface make the ZD621 healthcare printers easy to\nclean and sanitize, helping prevent the spread of infections in\nhospitals and clinics. And, the power supply is IEC 60601-1\ncompliant for use in healthcare facilities.\nExpect the Best\nPremier Printing Performance\nRely on the ZD621 to help you power through—day after day.\nFrom industry-leading print speeds to portability for\nElevating a Proven Winner\napplication flexibility to emerging technology to\nfield-installable options, the ZD621 stands apart. Available in\nExtending the ZD-Series Legacy direct thermal and thermal transfer healthcare models, and a\nZebra’s ZD620 Series printers are known for quality, premium RFID model*, the ZD621 supports a wide variety of\nperformance. As you select your next printer, you can be healthcare-specific use cases and requirements.\nconfident the next-generation ZD621 includes everything you\nloved in those legacy printers, and builds on this heritage to Operate with Ease\ndeliver best-in-class features for this new era of intelligence\nand forward adaptability.\nSimple to Deploy, Use, Manage and Secure\nBacked by Zebra’s innovative Print DNA software suite, the\nZD621 is incredibly simple to operate.\nThe ZD621 — Premium print quality, features and reliability.\nReady for tomorrow’s healthcare needs.\nFor more information, please visit www.zebra.com/zd621-healthcare\n--- Page 2 ---\nDeploy it anywhere with setup tools, wizards and emulation Movable Sensor for Comprehensive Media Compatibility\ncapabilities. The large, touch LED display and intuitive user The ZD621 movable media sensor lets you use virtually any\ninterface make operation easy with minimal training. See media for greater flexibility across a variety of use cases.\nstatus at a glance with the five LED icons. Take advantage of\nrobust remote management capabilities that alleviate IT Print DNA Software Suite, Your Built-In\nburdens. And, built-in security hardens your infrastructure\nAdvantage\nfrom cyberattacks.\nPut it to Work for Years Print Securely and Confidently, Without Hassles\nPrint DNA suite of software, powered by our Link-OS operating\nDesigned to Perform Today and Tomorrow system, will get your printer up and running quickly and\nsecurely. Print consistently, and uninterrupted with a solution\nTechnology is constantly advancing. So can your ZD621\nthat’s fully integrated and interoperable, and will enable your\nprinter. Featuring an innovative architecture, it’s engineered to\nprinter to evolve with your business needs.\npower future printing. In comparison, it’s 30% more powerful\nthan the ZD620 Series. This gives you the ability to run more\nUpdate, Troubleshoot and Monitor – All From a Single\ntasks, perform more operations simultaneously, maintain\nLocation\nsecurity and be ready for what’s next.\nWith Zebra’s Printer Profile Manager Enterprise, part of Print\nIntuitive User Interface DNA, you have the ability to easily manage, secure and\ntroubleshoot your networked printers from one remote\nInteract at a touch with the 4.3-in., full-color LCD touch display,\nlocation. Manage one printer, a group of specific printers or all\nstandard on the ZD621 healthcare and RFID models. The\nprinters anywhere in the world.\neasy-to- use menu features step-by-step setup wizards,\ntroubleshooting animations, media-loading and calibration\nUnparalleled, Peace-of-Mind Printer Security\nguidance and supports stand-alone printing applications.\nZebra touchscreens are expertly designed and tested for Shield yourself from cyberattacks with Zebra’s PrintSecure,\ntoughness and reliability consistent with Zebra’s printer part of Print DNA. Easily configure your printers via secure\nportfolio, including robust tolerance to temperature, humidity, connections, identify vulnerabilities, block unauthorized access\ndust and other environmental challenges. and more.\nConnect Your Way with Comprehensive Communication Explore Managed Print Services (MPS)\nIntegrate your ZD621 onto your existing wired and wireless with Assurance\nnetworks or connect it directly to any PC. Every ZD621 comes\nwith Ethernet, Serial, USB 2.0 and USB Host, or add an optional\nZebra’s Thermal Printers with Print DNA Make MPS Easy\ndual wireless radio with fast 802.11ac Wi-Fi and Bluetooth 4.1.\nLooking to gain control and visibility of your printer fleets with\nPrint from any Windows™, AndroidTM or iOS device, and\nMPS? With the Print DNA software suite, your Zebra MPS\nintegrate your ZD621 with Zebra’s printer setup mobile app\nprovider can remotely manage and optimize your printers,\nusing Bluetooth Low Energy (BLE). And with the included Print\ntrack and automate supplies replenishment and ensure\nTouch tag (NFC), you can simply tap a compatible mobile\nsecurity.\ndevice on the ZD621 to pair and print—as well as instantly\naccess Zebra’s extensive knowledge base of how-to videos.\nSupplies, Service and Support\nThe Features You Need, When You Need\nZebra Certified Supplies\nThem\nPrinting supplies provide a digital voice for assets across your\nsupply chain. You rely on them to disseminate critical data\nTurn Your ZD621 Into a Portable Printer\nthroughout your organization. That’s why we design, produce\nEasily transport your ZD621 healthcare printer on a cart or and rigorously pretest our own line of labels, tags and receipt\nwith Zebra’s optional carrying case, using the battery option. paper to ensure consistent, optimized performance in your\nPrint on- the-spot to reduce steps, increase productivity, and Zebra printer. For industry-leading quality, service and thermal\nimprove task accuracy. Power through a full shift with the printing expertise, choose Zebra Certified Supplies.\nhigh-capacity battery.\nService When You Need It\nZebra OneCare offers unmatched technical support direct\nfrom Zebra, as well as comprehensive repair services. And\nZebra’s Visibility Services provide real-time insights into printer\noperations to help optimize printer availability.\n--- Page 3 ---\nSpecifications\nMarkets and\nApplications\nHealthcare Features Options and Accessories\n• Healthcare preferred white color scheme Media Handling Dispenser/Peeler: label peel and present with\nHealthcare\n• Healthcare-compliant power supply, IEC 60601-1 certified label present sensor (factory installed or field\n• Disinfectant-ready, easy-to-clean plastics with sealed button installable) Cutter (factory installed or field\ninterface installable) • Prescription labels\n• UV-resistant housing supports UV cleaning protocols • Lab and specimen labels\nCommunication 802.11ac Wi-Fi and Bluetooth 4.1 (dual radio), • Patient ID wristbands\ns (factory installed or field installable) • Blood and IV bag labels\n• Patient record labels\nStandard Features\n• Asset labels\nBattery Provides power to the printer to support a full\nshift of printing at maximum print speed; •\n• Print methods: Thermal Transfer or Direct Thermal supports all connectivity and media handling\n• ZPL and EPL programming languages options\n• 4.3 in. full color touch LCD (resolution: 480 wide x 272 high) with\n3-button user interface\nCarrying Case² Carrying case with shoulder strap and\n• 5 status icons interface\nhandles makes it easy to bring your desktop\n• Ethernet, Serial, USB 2.0, USB Host\nprinter and battery to the point of application\n• Printer setup mobile app for Android & iOS via BLE\n(Bluetooth Low Energy 5) connection*\n• BLE is intended for use with Zebra printer setup mobile app only Keyboard Zebra Keyboard Display Unit (ZKDU) for\n• Real Time Clock (RTC) Display Unit stand- alone printing solutions\n• Media dancer for excellent print quality\n• OpenACCESSTM for easy media loading Media Locking Mechanical lock with 2 keys; Kensington™\n• Dual-wall frame construction Cabinet lock slot; available on ZD621 healthcare direct\n• ENERGY STAR™ certified thermal model only\n• ZebraDesigner Essentials – easy label design tool free at\nwww.zebra.com/zebradesigner\nEnclosed Power Attached power supply accessory for\nSupply cord-free installation\nPhysical Characteristics\nFonts/Graphics/Symbologies\nDimension Direct Thermal:\nBar Code Ratios 2:1 and 3:1\n8.7 in. L x 7.0 in. W x 5.9 in. H\n221 mm L x 177 mm W x 151 mm H\nThermal Transfer: 1D Bar Codes Code 11, Code 39, Code 93, Code 128,\n10.5 in. L x 8.0 in. W x 7.5 in. H ISBT-128, UPC-A, UPC-E, EAN-8, EAN-13, UPC\n267 mm L x 202 mm W x 192 mm H and EAN 2-or 5-digit extensions, Plessey,\nPostnet, Standard 2-of- 5, Industrial 2-of-5,\nInterleaved 2-of-5, Logmars, MSI, Codabar\nWeight Direct Thermal: 3.6 lbs./1.6 kg\nand Planet Code\nThermal Transfer: 5.5 lbs./2.5 kg\n2D Bar Codes Codablock, PDF417, Code 49, DataMatrix,\nMaxiCode, QR Code, MicroPDF, Aztec\nPrinter Specifications\nFonts and 16 resident expandable ZPL II bitmap fonts,\nOperating Link-OS™ Graphics two resident scalable ZPL fonts, five resident\nSystem expandable EPL2 fonts, native open-type font\nsupport, Unicode compliant. China units\ninclude SimSun simplified Chinese font\nResolution 203 dpi/8 dots per mm\n300 dpi/12 dots per mm (optional)\nMemory 512 MB Flash; 256 MB SDRAM Printers Supplies\n64 MB user available non-volatile memory\n8 MB user available SDRAM\nFor industry-leading quality, service and thermal printing\nexpertise, choose Zebra Certified Supplies to ensure consistent,\nMaximum Print 4.09 in./104 mm for 203 dpi optimized performance for your Zebra printer.\nWidth 4.27 in./108 mm for 300 dpi\nMaximum Print 8 in./203 mm per second (203 dpi)\nRegulatory\nSpeed 6 in./152 mm per second (300 dpi)\nMedia Sensors Full width, moveable reflective/black mark IEC 60950-1, IEC 62368-1, EN55022 Class B, EN55024, EN55035,\nsensor; multi-position transmissive/gap EN61000- 3-2, EN61000-3-3, FCC Class B, ICES-003, FCC 15.209;\nsensor 15.247(d), IC RSS 247, EN 300 328, EN 301 893, EN 62311, cTUVus\nCE Marking, VCCI, C-Tick, S-Mark, CCC, CU, BSMI, KCC, SABS,\nFirmware ZPL II; EPL 2; XML; ZBI; PDF Direct IN-Metro, BIS, NOM\nMedia and Ribbon Characteristics Environmental Compliance\nLabel Length Minimum: 0.25 in./6.4 mm Environment\nMaximum: 39.0 in./991 mm • RoHS Directive 2011/65/EU; Amendment 2015/863\nA complete list of product and materials compliance, please visit\nwww.zebra.com/environment\nMedia Width Direct Thermal: 0.585 in./15 mm to 4.25 in./\n108 mm\nThermal Transfer: 0.585 in./15 mm to 4.65 in./\n118 mm\nMedia Roll Size Maximum outer diameter: 5.0 in./127 mm\nCore inner diameter: 0.5 in. (12.7 mm) and 1.0\nin. (25.4 mm) standard, 1.5 in. (38.1), 2.0 in.,\n--- Page 4 ---\nMedia and Ribbon Characteristics Print DNA Software\n(50.8 mm) and 3.0 in. (76.2 mm) using This printer is supported by our Print DNA suite of software\noptional adapters capabilities to get your printer up and running quickly and\nsecurely, and enable your printer to evolve with your business\nMedia Thickness 0.003 in. (0.08 mm) min.; 0.0075 in. (0.19 mm) needs. Print DNA features may vary by model, and some features\nmax. (tear-off mode only) may require a license. For more information, please visit\nwww.zebra.com/printdna\nMedia Types Roll-fed or fan-fold, die cut or continuous with\nor without black mark, label or tag stock,\ncontinuous receipt paper, wristbands Included In The Box\nRibbon Outside 2.6 in./66 mm (300 m); 1.34 in./34 mm (74 m)\nPrinter, empty ribbon take-up cores (1 in. and 0.5 in.)*, 300 m\nDiameter\nribbon core adapters for non-Zebra ribbon (2)*, AC power supply,\npower cord(s), USB cable, Quick Start Guide, Regulatory Guide\nRibbon 984 ft. (300 m); 243 ft. (74 m) * Empty ribbon take-up cores and ribbon core adapters included\nStandard with ZD621 thermal transfer models only\nLength\nRibbon Ratio 1:4 ribbon to media (300 m)\n1:1 ribbon to media (74 m) Recommended Services\nRibbon Width 1.33 in./33.8 mm — 4.3 in./109.2 mm Zebra OneCare™ maintenance plans provide peak performance\nand device uptime while protecting your critical operations and\nRibbon Core I.D. 300 meter ribbon 1 in./25.4 mm your printers with defined service levels. For more information go\n74 meter ribbon 0.5 in./12.7 mm to\nwww.zebra.com/zebraonecare\nZebra OneCare Select: Comprehensive Coverage, including\nOperating Characteristics printheads, normal wear and accidental breakage\nPriority access 24x7 live technical support and software updates\nAdvance Replacement and Express Shipping (Next Day Device\nOperating 40° to 105° F/4.4° to 41° C\nReplacement)\nTemp.\nStandard Commissioning\nOnline Return Material Authorization (RMA) support\nStorage Temp. -40° to 140° F/-40° to 60° C\nZebra OneCare Essential: Comprehensive Coverage, including\nOperating 10% to 90% non-condensing printheads, normal wear and accidental breakage\nHumidity Priority access 8x5 live technical support and software updates\nThree-day depot repair turnaround time plus free return ground\nStorage 5% to 95% non-condensing shipping\nHumidity Online Return Material Authorization (RMA) support\nElectrical Auto-detectable (PFC Compliant) 100-240VAC, Note: Service availability may vary by region.\n50-60Hz; ENERGY STAR certified; Energy\nEfficiency Level VI certified; optional 2750\nmAh battery; Healthcare models include\nProduct Warranty\nIEC60601-1 certified power supply\nZD600 Series printers are warranted against defects in\nworkmanship and materials for a minimum period of 2 (two)\nyears from the date of shipment. Warranty varies by region. For\ncomplete warranty details, please visit\nwww.zebra.com/warranty\nFootnotes\nZD621 RFID model is not a healthcare-specific printerDoes not fit\nwith cutter or peeler attached\nThe Zebra wordmark and logo are trademarks of Zebra Technologies Corp., registered in many jurisdictions worldwide. Android is a\ntrademark of Google LLC. All other trademarks are the property of their respective owners. ©2025 Zebra Technologies Corp. and/or its\naffiliates.\n03/11/2024 HTML"
  },
  "specifications": {
    "printer": {
      "resolution": {
        "raw": "203 dpi/8 dots per mm\n300 dpi/12 dots per mm (optional)",
        "dpi": 203,
        "dots_per_mm": 8
      },
      "memory": "512 MB Flash; 256 MB SDRAM\n64 MB user available non-volatile memory\n8 MB user available SDRAM",
      "maximum_print_width": "4.09 in./104 mm for 203 dpi\n4.27 in./108 mm for 300 dpi",
      "media_sensors": [
        "Full width, moveable reflective/black mark sensor; multi-position transmissive/gap sensor"
      ],
      "firmware": [
        "ZPL II",
        "EPL 2",
        "XML",
        "ZBI",
        "PDF Direct"
      ]
    },
    "physical": {
      "dimensions": "Direct Thermal:\n8.7 in. L x 7.0 in. W x 5.9 in. H\n221 mm L x 177 mm W x 151 mm H\nThermal Transfer:\n10.5 in. L x 8.0 in. W x 7.5 in. H\n267 mm L x 202 mm W x 192 mm H",
      "weight": "Direct Thermal: 3.6 lbs./1.6 kg\nThermal Transfer: 5.5 lbs./2.5 kg"
    },
    "media": {
      "maximum_label_length": "Minimum: 0.25 in./6.4 mm\nMaximum: 39.0 in./991 mm",
      "media_width": {
        "raw": "Direct Thermal: 0.585 in./15 mm to 4.25 in./\n108 mm\nThermal Transfer: 0.585 in./15 mm to 4.65 in./\n118 mm",
        "min_inches": 0.585,
        "max_inches": 4.25
      },
      "media_roll_size": "Maximum outer diameter: 5.0 in./127 mm\nCore inner diameter: 0.5 in. (12.7 mm) and 1.0\nin. (25.4 mm) standard, 1.5 in. (38.1), 2.0 in.,",
      "thickness": "0.003 in. (0.08 mm) min.; 0.0075 in. (0.19 mm)\nmax. (tear-off mode only)",
      "media_types": [
        "Roll-fed or fan-fold",
        "Die cut or continuous with or without black mark",
        "Tag stock",
        "Continuous receipt paper",
        "Wristbands"
      ]
    },
    "ribbon": {
      "outside_diameter": {
        "raw": "2.6 in./66 mm (300 m); 1.34 in./34 mm (74 m)",
        "inches": 2.6,
        "mm": 66.0
      },
      "maximum_ribbon_length": "984 ft. (300 m); 243 ft. (74 m)",
      "ribbon_ratio": "1:4 ribbon to media (300 m)\n1:1 ribbon to media (74 m)",
      "ribbon_width": "1.33 in./33.8 mm — 4.3 in./109.2 mm",
      "ribbon_core_id": "300 meter ribbon 1 in./25.4 mm\n74 meter ribbon 0.5 in./12.7 mm"
    },
    "operating_conditions": {
      "operating_temperature": {
        "raw": "40° to 105° F/4.4° to 41° C",
        "min_f": 40,
        "max_f": 105,
        "min_c": 4.4,
        "max_c": 41.0
      },
      "storage_temperature": {
        "raw": "-40° to 140° F/-40° to 60° C",
        "min_f": -40,
        "max_f": 140,
        "min_c": -40.0,
        "max_c": 60.0
      },
      "operating_humidity": {
        "raw": "10% to 90% non-condensing",
        "min_percent": 10,
        "max_percent": 90,
        "condition": "non-condensing"
      },
      "storage_humidity": {
        "raw": "5% to 95% non-condensing",
        "min_percent": 5,
        "max_percent": 95,
        "condition": "non-condensing"
      },
      "electrical": "Auto-detectable (PFC Compliant) 100-240VAC,\n50-60Hz; ENERGY STAR certified; Energy\nEfficiency Level VI certified; optional 2750\nmAh battery; Healthcare models include\nIEC60601-1 certified power supply"
    }
  },
  "features": {
    "standard": [
      "Asset labels"
    ],
    "optional": [
      "Media Handling: Dispenser/Peeler: label peel and present with\nlabel present sensor (factory installed or field\ninstallable) Cutter (factory installed or field\ninstallable)",
      "Communication\ns: 802.11ac Wi-Fi and Bluetooth 4.1 (dual radio),\n(factory installed or field installable)",
      "Battery: Provides power to the printer to support a full\nshift of printing at maximum print speed;\nsupports all connectivity and media handling\noptions",
      "Carrying Case²: Carrying case with shoulder strap and\nhandles makes it easy to bring your desktop\nprinter and battery to the point of application",
      "Keyboard\nDisplay Unit: Zebra Keyboard Display Unit (ZKDU) for\nstand- alone printing solutions",
      "Media Locking\nCabinet: Mechanical lock with 2 keys; Kensington™\nlock slot; available on ZD621 healthcare direct\nthermal model only",
      "Enclosed Power\nSupply: Attached power supply accessory for\ncord-free installation"
    ]
  },
  "fonts_and_barcodes": {
    "fonts": [
      "16 resident expandable ZPL II bitmap fonts, two resident scalable ZPL fonts, five resident",
      "expandable EPL2 fonts, native open-type font",
      "support, Unicode compliant. China units",
      "include SimSun simplified Chinese font"
    ],
    "barcode_ratios": [
      "2:1",
      "3:1"
    ],
    "barcodes_1d": [
      "Code 11",
      "Code 39",
      "Code 93",
      "Code 128",
      "ISBT-128",
      "UPC-A",
      "UPC-E",
      "EAN-8",
      "EAN-13",
      "UPC and EAN 2-or 5-digit extensions",
      "Plessey",
      "Postnet",
      "Standard 2-of- 5",
      "Industrial 2-of-5",
      "Interleaved 2-of-5",
      "Logmars",
      "MSI",
      "Codabar and Planet Code"
    ],
    "barcodes_2d": [
      "Codablock",
      "PDF417",
      "Code 49",
      "DataMatrix",
      "MaxiCode",
      "QR Code",
      "MicroPDF",
      "Aztec"
    ],
    "graphics_memory": ""
  },
  "connectivity": [
    "Ethernet",
    "Wi-Fi",
    "Bluetooth",
    "Serial"
  ],
  "compliance": {
    "regulatory_standards": [
      "IEC 60950-1",
      "IEC 62368-1",
      "EN55022 Class B",
      "EN55024",
      "EN61000-3-3",
      "EN 300 328",
      "EN 301 893",
      "EN 62311",
      "FCC Class B",
      "FCC 15.209",
      "ICES-003",
      "IC RSS 247",
      "CE Marking",
      "cTUVus",
      "VCCI",
      "C-Tick",
      "S-Mark",
      "CCC",
      "CU",
      "BSMI",
      "KCC",
      "SABS",
      "IN-Metro",
      "BIS",
      "NOM"
    ],
    "certifications": [
      "CE Marking",
      "cTUVus",
      "ENERGY STAR"
    ],
    "energy_star": true
  },
  "warranty": {
    "duration_years": 2,
    "coverage": "IEC60601-1 certified power supply ZD600 Series printers are warranted against defects in workmanship and materials for a minimum period of 2 (two) years from the date of shipment. Warranty varies by region. For complete warranty details, please visit www.zebra.com/warranty Footnotes ZD621 RFID model is not a healthcare-specific printerDoes not fit with cutter or peeler attached",
    "url": "www.zebra.com/warranty"
  },
  "additional_information": {
    "Recommended Services": "Ribbon Width 1.33 in./33.8 mm — 4.3 in./109.2 mm Zebra OneCare™ maintenance plans provide peak performance and device uptime while protecting your critical operations and Ribbon Core I.D. 300 meter ribbon 1 in./25.4 mm your printers with defined service levels. For more information go 74 meter ribbon 0.5 in./12.7 mm to www.zebra.com/zebraonecare Zebra OneCare Select: Comprehensive Coverage, including Operating Characteristics printheads, normal wear and accidental breakage Priority access 24x7 live technical support and software updates Advance Replacement and Express Shipping (Next Day Device Operating 40° to 105° F/4.4° to 41° C Replacement) Temp. Standard Commissioning Online Return Material Authorization (RMA) support Storage Temp. -40° to 140° F/-40° to 60° C Zebra OneCare Essential: Comprehensive Coverage, including Operating 10% to 90% non-condensing printheads, normal wear and accidental breakage Humidity Priority access 8x5 live technical support and software updates Three-day depot repair turnaround time plus free return ground Storage 5% to 95% non-condensing shipping Humidity Online Return Material Authorization (RMA) support Electrical Auto-detectable (PFC Compliant) 100-240VAC, Note: Service availability may vary by region. 50-60Hz; ENERGY STAR certified; Energy Efficiency Level VI certified; optional 2750 mAh battery; Healthcare models include Product Warranty IEC60601-1 certified power supply ZD600 Series printers are warranted against defects in workmanship and materials for a minimum period of 2 (two) years from the date of shipment. Warranty varies by region. For complete warranty details, please visit www.zebra.com/warranty Footnotes ZD621 RFID model is not a healthcare-specific printerDoes not fit with cutter or peeler attached The Zebra wordmark and logo are trademarks of Zebra Technologies Corp., registered in many jurisdictions worldwide. Android is a trademark of Google LLC. All other trademarks are the property of their respective owners. ©2025 Zebra Technologies Corp. and/or its affiliates. 03/11/2024 HTML",
    "ZebraOneCare": "Zebra OneCare Select: Comprehensive Coverage, including Operating Characteristics printheads, normal wear and accidental breakage Priority access 24x7 live technical support and software updates Advance Replacement and Express Shipping (Next Day Device Operating 40° to 105° F/4.4° to 41° C Replacement) Temp. Standard Commissioning Online Return Material Authorization (RMA) support Storage Temp. -40° to 140° F/-40° to 60° C Zebra OneCare Essential: Comprehensive Coverage, including Operating 10% to 90% non-condensing printheads, normal wear and accidental breakage Humidity Priority access 8x5 live technical support and software updates Three-day depot repair turnaround time plus free return ground Storage 5% to 95% non-condensing shipping Humidity Online Return Material Authorization (RMA) support Electrical Auto-detectable (PFC Compliant) 100-240VAC,",
    "Print DNA": "suite, the ZD621 is incredibly simple to operate. The ZD621 — Premium print quality, features and reliability. Ready for tomorrow’s healthcare needs. For more information, please visit www.zebra.com/zd621-healthcare --- Page 2 --- Deploy it anywhere with setup tools, wizards and emulation Movable Sensor for Comprehensive Media Compatibility capabilities. The large, touch LED display and intuitive user The ZD621 movable media sensor lets you use virtually any interface make operation easy with minimal training. See media for greater flexibility across a variety of use cases. status at a glance with the five LED icons. Take advantage of robust remote management capabilities that alleviate IT Print DNA Software Suite, Your Built-In burdens. And, built-in security hardens your infrastructure Advantage from cyberattacks. Put it to Work for Years Print Securely and Confidently, Without Hassles Print DNA suite of software, powered by our Link-OS operating Designed to Perform Today and Tomorrow system, will get your printer up and running quickly and securely. Print consistently, and uninterrupted with a solution Technology is constantly advancing. So can your ZD621 that’s fully integrated and interoperable, and will enable your printer. Featuring an innovative architecture, it’s engineered to printer to evolve with your business needs. power future printing. In comparison, it’s 30% more powerful than the ZD620 Series. This gives you the ability to run more Update, Troubleshoot and Monitor – All From a Single tasks, perform more operations simultaneously, maintain Location security and be ready for what’s next. With Zebra’s Printer Profile Manager Enterprise, part of Print Intuitive User Interface DNA, you have the ability to easily manage, secure and troubleshoot your networked printers from one remote Interact at a touch with the 4.3-in., full-color LCD touch display, location. Manage one printer, a group of specific printers or all standard on the ZD621 healthcare and RFID models. The printers anywhere in the world. easy-to- use menu features step-by-step setup wizards, troubleshooting animations, media-loading and calibration Unparalleled, Peace-of-Mind Printer Security guidance and supports stand-alone printing applications. Zebra touchscreens are expertly designed and tested for Shield yourself from cyberattacks with Zebra’s PrintSecure, toughness and reliability consistent with Zebra’s printer part of Print DNA. Easily configure your printers via secure portfolio, including robust tolerance to temperature, humidity, connections, identify vulnerabilities, block unauthorized access dust and other environmental challenges. and more. Connect Your Way with Comprehensive Communication Explore Managed Print Services (MPS) Integrate your ZD621 onto your existing wired and wireless with Assurance networks or connect it directly to any PC. Every ZD621 comes with Ethernet, Serial, USB 2.0 and USB Host, or add an optional Zebra’s Thermal Printers with Print DNA Make MPS Easy dual wireless radio with fast 802.11ac Wi-Fi and Bluetooth 4.1. Looking to gain control and visibility of your printer fleets with Print from any Windows™, AndroidTM or iOS device, and MPS? With the Print DNA software suite, your Zebra MPS integrate your ZD621 with Zebra’s printer setup mobile app provider can remotely manage and optimize your printers, using Bluetooth Low Energy (BLE). And with the included Print track and automate supplies replenishment and ensure Touch tag (NFC), you can simply tap a compatible mobile security. device on the ZD621 to pair and print—as well as instantly access Zebra’s extensive knowledge base of how-to videos. Supplies, Service and Support The Features You Need, When You Need Zebra Certified Supplies Them Printing supplies provide a digital voice for assets across your supply chain. You rely on them to disseminate critical data Turn Your ZD621 Into a Portable Printer throughout your organization. That’s why we design, produce Easily transport your ZD621 healthcare printer on a cart or and rigorously pretest our own line of labels, tags and receipt with Zebra’s optional carrying case, using the battery option. paper to ensure consistent, optimized performance in your Print on- the-spot to reduce steps, increase productivity, and Zebra printer. For industry-leading quality, service and thermal improve task accuracy. Power through a full shift with the printing expertise, choose Zebra Certified Supplies. high-capacity battery. Service When You Need It Zebra OneCare offers unmatched technical support direct from Zebra, as well as comprehensive repair services. And Zebra’s Visibility Services provide real-time insights into printer operations to help optimize printer availability. --- Page 3 --- Specifications Markets and Applications Healthcare Features Options and Accessories • Healthcare preferred white color scheme Media Handling Dispenser/Peeler: label peel and present with Healthcare • Healthcare-compliant power supply, IEC 60601-1 certified label present sensor (factory installed or field • Disinfectant-ready, easy-to-clean plastics with sealed button installable) Cutter (factory installed or field interface installable) • Prescription labels • UV-resistant housing supports UV cleaning protocols • Lab and specimen labels Communication 802.11ac Wi-Fi and Bluetooth 4.1 (dual radio), • Patient ID wristbands s (factory installed or field installable) • Blood and IV bag labels • Patient record labels Standard Features • Asset labels Battery Provides power to the printer to support a full shift of printing at maximum print speed; • • Print methods: Thermal Transfer or Direct Thermal supports all connectivity and media handling • ZPL and EPL programming languages options • 4.3 in. full color touch LCD (resolution: 480 wide x 272 high) with 3-button user interface Carrying Case² Carrying case with shoulder strap and • 5 status icons interface handles makes it easy to bring your desktop • Ethernet, Serial, USB 2.0, USB Host printer and battery to the point of application • Printer setup mobile app for Android & iOS via BLE (Bluetooth Low Energy 5) connection* • BLE is intended for use with Zebra printer setup mobile app only Keyboard Zebra Keyboard Display Unit (ZKDU) for • Real Time Clock (RTC) Display Unit stand- alone printing solutions • Media dancer for excellent print quality • OpenACCESSTM for easy media loading Media Locking Mechanical lock with 2 keys; Kensington™ • Dual-wall frame construction Cabinet lock slot; available on ZD621 healthcare direct • ENERGY STAR™ certified thermal model only • ZebraDesigner Essentials – easy label design tool free at www.zebra.com/zebradesigner Enclosed Power Attached power supply accessory for Supply cord-free installation Physical Characteristics Fonts/Graphics/Symbologies Dimension Direct Thermal: Bar Code Ratios 2:1 and 3:1 8.7 in. L x 7.0 in. W x 5.9 in. H 221 mm L x 177 mm W x 151 mm H Thermal Transfer: 1D Bar Codes Code 11, Code 39, Code 93, Code 128, 10.5 in. L x 8.0 in. W x 7.5 in. H ISBT-128, UPC-A, UPC-E, EAN-8, EAN-13, UPC 267 mm L x 202 mm W x 192 mm H and EAN 2-or 5-digit extensions, Plessey, Postnet, Standard 2-of- 5, Industrial 2-of-5, Interleaved 2-of-5, Logmars, MSI, Codabar Weight Direct Thermal: 3.6 lbs./1.6 kg and Planet Code Thermal Transfer: 5.5 lbs./2.5 kg 2D Bar Codes Codablock, PDF417, Code 49, DataMatrix, MaxiCode, QR Code, MicroPDF, Aztec Printer Specifications Fonts and 16 resident expandable ZPL II bitmap fonts, Operating Link-OS™ Graphics two resident scalable ZPL fonts, five resident System expandable EPL2 fonts, native open-type font support, Unicode compliant. China units include SimSun simplified Chinese font Resolution 203 dpi/8 dots per mm 300 dpi/12 dots per mm (optional) Memory 512 MB Flash; 256 MB SDRAM Printers Supplies 64 MB user available non-volatile memory 8 MB user available SDRAM For industry-leading quality, service and thermal printing expertise, choose Zebra Certified Supplies to ensure consistent, Maximum Print 4.09 in./104 mm for 203 dpi optimized performance for your Zebra printer. Width 4.27 in./108 mm for 300 dpi Maximum Print 8 in./203 mm per second (203 dpi) Regulatory Speed 6 in./152 mm per second (300 dpi) Media Sensors Full width, moveable reflective/black mark IEC 60950-1, IEC 62368-1, EN55022 Class B, EN55024, EN55035, sensor; multi-position transmissive/gap EN61000- 3-2, EN61000-3-3, FCC Class B, ICES-003, FCC 15.209; sensor 15.247(d), IC RSS 247, EN 300 328, EN 301 893, EN 62311, cTUVus CE Marking, VCCI, C-Tick, S-Mark, CCC, CU, BSMI, KCC, SABS, Firmware ZPL II; EPL 2; XML; ZBI; PDF Direct IN-Metro, BIS, NOM Media and Ribbon Characteristics Environmental Compliance Label Length Minimum: 0.25 in./6.4 mm Environment Maximum: 39.0 in./991 mm • RoHS Directive 2011/65/EU; Amendment 2015/863 A complete list of product and materials compliance, please visit www.zebra.com/environment Media Width Direct Thermal: 0.585 in./15 mm to 4.25 in./ 108 mm Thermal Transfer: 0.585 in./15 mm to 4.65 in./ 118 mm Media Roll Size Maximum outer diameter: 5.0 in./127 mm Core inner diameter: 0.5 in. (12.7 mm) and 1.0 in. (25.4 mm) standard, 1.5 in. (38.1), 2.0 in., --- Page 4 --- Media and Ribbon Characteristics Print DNA Software (50.8 mm) and 3.0 in. (76.2 mm) using This printer is supported by our Print DNA suite of software optional adapters capabilities to get your printer up and running quickly and securely, and enable your printer to evolve with your business Media Thickness 0.003 in. (0.08 mm) min.; 0.0075 in. (0.19 mm) needs. Print DNA features may vary by model, and some features max. (tear-off mode only) may require a license. For more information, please visit www.zebra.com/printdna Media Types Roll-fed or fan-fold, die cut or continuous with or without black mark, label or tag stock, continuous receipt paper, wristbands Included In The Box Ribbon Outside 2.6 in./66 mm (300 m); 1.34 in./34 mm (74 m) Printer, empty ribbon take-up cores (1 in. and 0.5 in.)*, 300 m Diameter ribbon core adapters for non-Zebra ribbon (2)*, AC power supply, power cord(s), USB cable, Quick Start Guide, Regulatory Guide Ribbon 984 ft. (300 m); 243 ft. (74 m) * Empty ribbon take-up cores and ribbon core adapters included Standard with ZD621 thermal transfer models only Length Ribbon Ratio 1:4 ribbon to media (300 m) 1:1 ribbon to media (74 m) Recommended Services Ribbon Width 1.33 in./33.8 mm — 4.3 in./109.2 mm Zebra OneCare™ maintenance plans provide peak performance and device uptime while protecting your critical operations and Ribbon Core I.D. 300 meter ribbon 1 in./25.4 mm your printers with defined service levels. For more information go 74 meter ribbon 0.5 in./12.7 mm to www.zebra.com/zebraonecare Zebra OneCare Select: Comprehensive Coverage, including Operating Characteristics printheads, normal wear and accidental breakage Priority access 24x7 live technical support and software updates Advance Replacement and Express Shipping (Next Day Device Operating 40° to 105° F/4.4° to 41° C Replacement) Temp. Standard Commissioning Online Return Material Authorization (RMA) support Storage Temp. -40° to 140° F/-40° to 60° C Zebra OneCare Essential: Comprehensive Coverage, including Operating 10% to 90% non-condensing printheads, normal wear and accidental breakage Humidity Priority access 8x5 live technical support and software updates Three-day depot repair turnaround time plus free return ground Storage 5% to 95% non-condensing shipping Humidity Online Return Material Authorization (RMA) support Electrical Auto-detectable (PFC Compliant) 100-240VAC, Note: Service availability may vary by region. 50-60Hz; ENERGY STAR certified; Energy Efficiency Level VI certified; optional 2750 mAh battery; Healthcare models include",
    "Printer Supplies": "64 MB user available non-volatile memory 8 MB user available SDRAM For industry-leading quality, service and thermal printing expertise, choose Zebra Certified Supplies to ensure consistent, Maximum Print 4.09 in./104 mm for 203 dpi optimized performance for your Zebra printer. Width 4.27 in./108 mm for 300 dpi Maximum Print 8 in./203 mm per second (203 dpi)",
    "Print DNA Components": {
      "ZebraDesigner Essentials": "– easy label design tool free at www.zebra.com/zebradesigner Enclosed Power Attached power supply accessory for Supply cord-free installation Physical Characteristics Fonts/Graphics/Symbologies Dimension Direct Thermal: Bar Code Ratios 2:1 and 3:1 8.7 in. L x 7.0 in. W x 5.9 in. H 221 mm L x 177 mm W x 151 mm H Thermal Transfer: 1D Bar Codes Code 11, Code 39, Code 93, Code 128, 10.5 in. L x 8.0 in. W x 7.5 in. H ISBT-128, UPC-A, UPC-E, EAN-8, EAN-13, UPC 267 mm L x 202 mm W x 192 mm H and EAN 2-or 5-digit extensions, Plessey, Postnet, Standard 2-of- 5, Industrial 2-of-5, Interleaved 2-of-5, Logmars, MSI, Codabar Weight Direct Thermal: 3.6 lbs./1.6 kg and Planet Code Thermal Transfer: 5.5 lbs./2.5 kg 2D Bar Codes Codablock, PDF417, Code 49, DataMatrix, MaxiCode, QR Code, MicroPDF, Aztec Printer Specifications Fonts and 16 resident expandable ZPL II bitmap fonts, Operating Link-OS™ Graphics two resident scalable ZPL fonts, five resident System expandable EPL2 fonts, native open-type font support, Unicode compliant. China units include SimSun simplified Chinese font Resolution 203 dpi/8 dots per mm 300 dpi/12 dots per mm (optional) Memory 512 MB Flash; 256 MB SDRAM Printers Supplies 64 MB user available non-volatile memory 8 MB user available SDRAM For industry-leading quality, service and thermal printing expertise, choose Zebra Certified Supplies to ensure consistent, Maximum Print 4.09 in./104 mm for 203 dpi optimized performance for your Zebra printer. Width 4.27 in./108 mm for 300 dpi Maximum Print 8 in./203 mm per second (203 dpi) Regulatory Speed 6 in./152 mm per second (300 dpi) Media Sensors Full width, moveable reflective/black mark IEC 60950-1, IEC 62368-1, EN55022 Class B, EN55024, EN55035, sensor; multi-position transmissive/gap EN61000- 3-2, EN61000-3-3, FCC Class B, ICES-003, FCC 15.209; sensor 15.247(d), IC RSS 247, EN 300 328, EN 301 893, EN 62311, cTUVus CE Marking, VCCI, C-Tick, S-Mark, CCC, CU, BSMI, KCC, SABS, Firmware ZPL II; EPL 2; XML; ZBI; PDF Direct IN-Metro, BIS, NOM Media and Ribbon Characteristics Environmental Compliance Label Length Minimum: 0.25 in./6.4 mm Environment Maximum: 39.0 in./991 mm • RoHS Directive 2011/65/EU; Amendment 2015/863 A complete list of product and materials compliance, please visit www.zebra.com/environment Media Width Direct Thermal: 0.585 in./15 mm to 4.25 in./ 108 mm Thermal Transfer: 0.585 in./15 mm to 4.65 in./ 118 mm Media Roll Size Maximum outer diameter: 5.0 in./127 mm Core inner diameter: 0.5 in. (12.7 mm) and 1.0 in. (25.4 mm) standard, 1.5 in. (38.1), 2.0 in., --- Page 4 --- Media and Ribbon Characteristics Print DNA Software (50.8 mm) and 3.0 in. (76.2 mm) using This printer is supported by our Print DNA suite of software optional adapters capabilities to get your printer up and running quickly and securely, and enable your printer to evolve with your business Media Thickness 0.003 in. (0.08 mm) min.; 0.0075 in. (0.19 mm) needs. Print DNA features may vary by model, and some features max. (tear-off mode only) may require a license."
    },
    "notes": [
      "Service availability may vary by region. 50-60Hz; ENERGY STAR certified; Energy Efficiency Level VI certified; optional 2750 mAh battery; Healthcare models include Product Warranty IEC60601-1 certified power supply ZD600 Series printers are warranted against defects in workmanship and materials for a minimum period of 2 (two) years from the date of shipment. Warranty varies by region. For complete warranty details, please visit www.zebra.com/warranty Footnotes ZD621 RFID model is not a healthcare-specific printerDoes not fit with cutter or peeler attached The Zebra wordmark and logo are trademarks of Zebra Technologies Corp., registered in many jurisdictions worldwide. Android is a trademark of Google LLC. All other trademarks are the property of their respective owners. ©2025 Zebra Technologies Corp. and/or its affiliates. 03/11/2024 HTML"
    ],
    "copyright": "©2025 Zebra Technologies Corp. and/or its",
    "trademark": "The Zebra wordmark and logo are trademarks of Zebra Technologies Corp.",
    "document_date": "03/11/2024"
  },
  "metadata": {
    "source_file": "zd621-healthcare-series-spec-sheet-en-us.pdf",
    "extraction_date": "2025-10-16T13:47:51.372499",
    "schema_version": "1.0.0",
    "total_pages": 4,
    "total_tables": 17
  }
}